Workbook
Name pivot1: 'pivot and charts'!$A$3:$B$12
Name Slicer_Customer_Type: #N/A
Name Slicer_Month: #N/A
Name Slicer_Payment_Method: #N/A
Name Slicer_Region: #N/A

Sheet uncleaned_sales data
A1: Order ID | B1: Date | C1: Salesperson | D1: Region | E1: Category | F1: Product Name | G1: Units Sold | H1: Unit Price (PKR) | I1: Discount % | J1: Total Revenue (PKR) | K1: Cost Price (Unit) | L1: Total Cost (PKR) | M1: Customer Type | N1: Payment Method | O1: Delivery Status
A2: ORD-1002 | B2: 2024-10-06 | C2: Sara Khan | D2: Faisalabad | E2: Electronics | F2: Mobile Phone | G2: 3 | H2: 25000 | I2: 5 | J2: 71250 | K2: 18000 | L2: 54000 | N2: EasyPaisa | O2: Pending
A3: ORD-1005 | B3: 2024-06-25 | C3: Nadia Iqbal | D3: Quetta | E3: Electronics | F3: Headphones | H3: 5000 | I3: 0 | J3: 90000 | K3: 3000 | L3: 54000 | M3: Returning | N3: Cash | O3: Delivered
A4: ORD-1012 | B4: 2024-03-11 | C4: Kamran Sheikh | D4: Rawalpindi | E4: Electronics | F4: Mobile Phone | G4: 4 | H4: 25000 | I4: 5 | J4: 95000 | K4: 18000 | L4: 72000 | M4: New | N4: Bank Transfer | O4: Delivered
A5: ORD-1021 | B5: 2024-11-19 | C5: Ahmed Ali | D5: Peshawar | E5: Electronics | F5: Mobile Phone | G5: 11 | H5: 25000 | I5: 0 | J5: 275000 | K5: 18000 | L5: 198000 | M5: New | N5: Debit Card | O5: Pending
A6: ORD-1026 | B6: 2024-11-29 | C6: Kamran Sheikh | D6: Karachi | E6: Electronics | F6: Laptop | G6: 6 | H6: 85000 | I6: 15 | J6: 433500 | K6: 65000 | L6: 390000 | M6: Returning | N6: JazzCash | O6: Delivered
A7: ORD-1030 | B7: 2024-02-04 | C7: Fatima Malik | D7: Faisalabad | E7: Electronics | F7: Smartwatch | G7: 8 | H7: 15000 | I7: 20 | J7: 96000 | K7: 10000 | L7: 80000 | M7: New | N7: EasyPaisa | O7: Delivered
A8: ORD-1041 | B8: 2024-05-07 | C8: Usman Raza | D8: Karachi | E8: Electronics | F8: Headphones | G8: 2 | H8: 5000 | I8: 15 | J8: 8500 | K8: 3000 | L8: 6000 | M8: New | N8: Credit Card | O8: Shipped
A9: ORD-1044 | B9: 2024-05-13 | C9: Bilal Hussain | D9: Quetta | E9: Electronics | F9: Mobile Phone | G9: 20 | H9: 25000 | I9: 15 | J9: 425000 | K9: 18000 | L9: 360000 | M9: Returning | N9: Bank Transfer | O9: Shipped
A10: ORD-1051 | B10: 2024-04-11 | C10: Bilal Hussain | D10: Karachi | E10: Electronics | F10: Laptop | G10: 16 | H10: 85000 | I10: 20 | J10: 1088000 | K10: 65000 | L10: 1040000 | M10: New | N10: JazzCash | O10: Delivered
A11: ORD-1057 | B11: 2024-12-21 | C11: Bilal Hussain | D11: Karachi | E11: Electronics | F11: Headphones | G11: 14 | H11: 5000 | I11: 10 | J11: 63000 | K11: 3000 | L11: 42000 | M11: Returning | N11: JazzCash | O11: Delivered
A12: ORD-1066 | B12: 2024-07-11 | C12: Hassan Mirza | D12: Peshawar | E12: Electronics | F12: Smartwatch | G12: 8 | H12: 15000 | I12: 0 | J12: 120000 | K12: 10000 | L12: 80000 | M12: Returning | N12: Bank Transfer
A13: ORD-1088 | B13: 2024-08-09 | C13: Ayesha Siddiqui | D13: Quetta | E13: Electronics | F13: Mobile Phone | G13: 8 | H13: 25000 | I13: 25 | J13: 150000 | K13: 18000 | L13: 144000 | M13: New | N13: Bank Transfer | O13: Shipped
A14: ORD-1095 | B14: 2024-04-25 | C14: Sara Khan | D14: Rawalpindi | E14: Electronics | F14: Laptop | G14: 16 | H14: 85000 | I14: 25 | J14: 1020000 | K14: 65000 | L14: 1040000 | M14: Returning | N14: EasyPaisa | O14: Pending
A15: ORD-1101 | B15: 2024-03-05 | C15: Kamran Sheikh | D15: Multan | E15: Electronics | F15: laptop | G15: 4 | H15: 5000 | I15: 20 | J15: 16000 | K15: 3000 | L15: 12000 | M15: Returning | O15: Pending
A16: ORD-1105 | B16: 2024-01-15 | C16: Ahmed Ali | D16: Multan | E16: Electronics | F16: laptop | G16: 12 | H16: 35000 | I16: 10 | J16: 378000 | K16: 26000 | L16: 312000 | M16: Returning | N16: Credit Card | O16: Delivered
A17: ORD-1108 | B17: 2024-08-26 | C17: Usman Raza | D17: Islamabad | E17: Electronics | F17: Headphones | G17: 12 | H17: 5000 | I17: 20 | J17: 48000 | K17: 3000 | L17: 36000 | M17: Returning | N17: Bank Transfer | O17: Cancelled
A18: ORD-1112 | B18: 2024-05-08 | C18: Bilal Hussain | D18: Lahor | E18: Electronics | F18: Tablet | G18: 15 | H18: 35000 | I18: 0 | J18: 525000 | K18: 26000 | L18: 390000 | M18: Returning | N18: Bank Transfer | O18: Delivered
A19: ORD-1115 | B19: 2024-04-25 | C19: Hassan Mirza | D19: Multan | E19: Electronics | F19: Headphones | G19: 1 | H19: 5000 | I19: 10 | J19: 4500 | K19: 3000 | L19: 3000 | N19: JazzCash | O19: Delivered
A20: ORD-1117 | B20: 2024-10-14 | C20: Ayesha Siddiqui | D20: Peshawar | E20: Electronics | F20: Headphones | G20: 10 | H20: 5000 | I20: 25 | J20: 37500 | K20: 3000 | L20: 30000 | M20: Returning | N20: Cash | O20: Delivered
A21: ORD-1118 | B21: 2024-01-20 | C21: Usman Raza | D21: Rawalpindi | E21: Electronics | F21: Mobile Phone | G21: 8 | H21: 25000 | I21: 20 | J21: 160000 | K21: 18000 | L21: 144000 | M21: New | N21: JazzCash | O21: Delivered
A22: ORD-1121 | B22: 2024-07-07 | C22: Kamran Sheikh | D22: Multan | E22: Electronics | F22: laptop | G22: 9 | H22: 5000 | J22: 42750 | K22: 3000 | L22: 27000 | M22: New | N22: JazzCash | O22: Delivered
A23: ORD-1122 | B23: 2024-04-18 | C23: Nadia Iqbal | D23: Karachi | E23: Electronics | F23: Tablet | G23: 8 | H23: 35000 | I23: 5 | J23: 266000 | K23: 26000 | L23: 208000 | M23: New | N23: Cash | O23: Shipped
A24: ORD-1125 | B24: 2024-05-01 | C24: Nadia Iqbal | D24: Multan | E24: Electronics | F24: Laptop | G24: 9 | H24: 85000 | I24: 0 | J24: 765000 | K24: 65000 | L24: 585000 | M24: New | N24: Bank Transfer | O24: Delivered
A25: ORD-1128 | B25: 2024-09-08 | C25: Zara Butt | D25: Lahore | E25: Electronics | F25: Tablet | G25: 20 | H25: 35000 | I25: 5 | J25: 665000 | K25: 26000 | L25: 520000 | M25: New | N25: Credit Card | O25: Delivered
A26: ORD-1132 | B26: 2024-02-13 | C26: Sara Khan | D26: Faisalabad | E26: Electronics | F26: Tablet | G26: 5 | H26: 35000 | I26: 20 | J26: 140000 | K26: 26000 | L26: 130000 | M26: New | O26: Cancelled
A27: ORD-1137 | B27: 2024-03-14 | C27: Nadia Iqbal | D27: Faisalabad | E27: Electronics | F27: Laptop | G27: 1 | H27: 85000 | I27: 0 | J27: 85000 | K27: 65000 | L27: 65000 | M27: New | N27: JazzCash | O27: Delivered
A28: ORD-1142 | B28: 2024-05-10 | C28: Usman Raza | D28: Multan | E28: Electronics | F28: Mobile Phone | G28: 16 | H28: 25000 | I28: 25 | J28: 300000 | K28: 18000 | L28: 288000 | M28: Returning | N28: Credit Card | O28: Delivered
A29: ORD-1143 | B29: 2024-09-29 | C29: Fatima Malik | D29: Multan | E29: Electronics | F29: Headphones | G29: 2 | H29: 5000 | I29: 15 | J29: 8500 | K29: 3000 | L29: 6000 | M29: New | N29: JazzCash | O29: Cancelled
A30: ORD-1148 | B30: 2024-03-29 | C30: Nadia Iqbal | D30: Islamabad | E30: Electronics | F30: Laptop | G30: 16 | H30: 85000 | I30: 15 | J30: 1156000 | K30: 65000 | L30: 1040000 | M30: Returning | N30: Bank Transfer | O30: Cancelled
A31: ORD-1151 | B31: 2024-07-07 | C31: Usman Raza | D31: Lahore | E31: Electronics | F31: Smartwatch | G31: 20 | H31: 15000 | I31: 20 | J31: 240000 | K31: 10000 | L31: 200000 | M31: Returning | N31: JazzCash | O31: Delivered
A32: ORD-1153 | B32: 2024-06-24 | C32: Sara Khan | D32: Islamabad | E32: Electronics | F32: Laptop | G32: 15 | H32: 85000 | I32: 15 | J32: 1083750 | K32: 65000 | L32: 975000 | M32: New | O32: Delivered
A33: ORD-1164 | B33: 2024-09-19 | C33: Bilal Hussain | D33: Faisalabad | E33: Electronics | F33: Laptop | H33: 85000 | I33: 10 | J33: 1147500 | K33: 65000 | L33: 975000 | M33: New | N33: JazzCash | O33: Delivered
A34: ORD-1167 | B34: 2024-11-11 | C34: Ahmed Ali | D34: Lahore | E34: Electronics | F34: Tablet | G34: 7 | H34: 35000 | I34: 5 | J34: 232750 | K34: 26000 | L34: 182000 | N34: Cash | O34: Shipped
A35: ORD-1168 | B35: 2024-05-01 | C35: Usman Raza | D35: Lahore | E35: Electronics | F35: Laptop | H35: 85000 | I35: 25 | J35: 892500 | K35: 65000 | L35: 910000 | M35: Returning | N35: Cash | O35: Delivered
A36: ORD-1175 | B36: 2024-10-05 | C36: Zara Butt | D36: Quetta | E36: Electronics | F36: Laptop | G36: 10 | H36: 85000 | I36: 10 | J36: 765000 | K36: 65000 | L36: 650000 | M36: New | N36: Bank Transfer | O36: Delivered
A37: ORD-1177 | B37: 2024-07-07 | C37: Kamran Sheikh | D37: Quetta | E37: Electronics | F37: Headphones | G37: 3 | H37: 5000 | I37: 15 | J37: 12750 | K37: 3000 | L37: 9000 | M37: New | N37: EasyPaisa | O37: Delivered
A38: ORD-1180 | B38: 2024-07-26 | C38: Ayesha Siddiqui | D38: Islamabad | E38: Electronics | F38: Laptop | G38: 20 | H38: 85000 | I38: 25 | J38: 1275000 | K38: 65000 | L38: 1300000 | M38: Returning | N38: Cash | O38: Delivered
A39: ORD-1182 | B39: 2024-07-08 | C39: Ayesha Siddiqui | D39: Rawalpindi | E39: Electronics | F39: Smartwatch | G39: 5 | H39: 15000 | I39: 20 | J39: 60000 | K39: 10000 | L39: 50000 | M39: Returning | N39: JazzCash | O39: Delivered
A40: ORD-1183 | B40: 2024-05-22 | C40: Fatima Malik | D40: Lahore | E40: Electronics | F40: Laptop | G40: 16 | H40: 85000 | I40: 20 | J40: 1088000 | K40: 65000 | L40: 1040000 | M40: Returning | N40: EasyPaisa | O40: Delivered
A41: ORD-1185 | B41: 2024-08-19 | C41: Bilal Hussain | D41: Rawalpindi | E41: Electronics | F41: Tablet | G41: 12 | H41: 35000 | I41: 25 | J41: 315000 | K41: 26000 | L41: 312000 | M41: New | N41: EasyPaisa | O41: Delivered
A42: ORD-1217 | B42: 2024-09-28 | C42: Fatima Malik | D42: Peshawar | E42: Electronics | F42: Mobile Phone | G42: 14 | H42: 25000 | J42: 315000 | K42: 18000 | L42: 252000 | M42: Returning | N42: Cash | O42: Pending
A43: ORD-1230 | B43: 2024-03-25 | C43: Ayesha Siddiqui | D43: Rawalpindi | E43: Electronics | F43: Laptop | G43: 19 | H43: 85000 | I43: 15 | J43: 1372750 | K43: 65000 | L43: 1235000 | M43: New | N43: EasyPaisa | O43: Delivered
A44: ORD-1233 | B44: 2024-12-24 | C44: Sara Khan | D44: Karachi | E44: Electronics | F44: Headphones | G44: 2 | H44: 5000 | I44: 10 | J44: 9000 | K44: 3000 | L44: 6000 | M44: Returning | N44: Credit Card | O44: Shipped
A45: ORD-1235 | B45: 2024-10-03 | C45: Bilal Hussain | D45: Multan | E45: Electronics | F45: laptop | G45: 18 | H45: 85000 | I45: 15 | J45: 1300500 | K45: 65000 | L45: 1170000 | M45: New | N45: Bank Transfer | O45: Returned
A46: ORD-1238 | B46: 2024-01-09 | C46: Fatima Malik | D46: Peshawar | E46: Electronics | F46: Mobile Phone | G46: 20 | H46: 25000 | I46: 0 | J46: 500000 | K46: 18000 | L46: 360000 | M46: Returning | N46: EasyPaisa | O46: Pending
A47: ORD-1246 | B47: 2024-12-10 | C47: Nadia Iqbal | D47: Karachi | E47: Electronics | F47: Laptop | G47: 19 | H47: 85000 | I47: 25 | J47: 1211250 | K47: 65000 | L47: 1235000 | M47: New | N47: JazzCash | O47: Delivered
A48: ORD-1256 | B48: 2024-10-09 | C48: Hassan Mirza | D48: Karachi | E48: Electronics | F48: Smartwatch | G48: 9 | H48: 15000 | I48: 20 | J48: 108000 | K48: 10000 | L48: 90000 | M48: Returning | N48: Cash | O48: Delivered
A49: ORD-1257 | B49: 2024-12-23 | C49: Hassan Mirza | D49: Islamabad | E49: Electronics | F49: Mobile Phone | G49: 17 | H49: 25000 | I49: 5 | J49: 403750 | K49: 18000 | L49: 306000 | M49: New | N49: Credit Card | O49: Pending
A50: ORD-1259 | B50: 2024-12-22 | C50: Fatima Malik | D50: Quetta | E50: Electronics | F50: Mobile Phone | G50: 3 | H50: 25000 | I50: 15 | J50: 63750 | K50: 18000 | L50: 54000 | M50: Returning | N50: JazzCash
A51: ORD-1260 | B51: 2024-01-29 | C51: Ahmed Ali | D51: Islamabad | E51: Electronics | F51: Headphones | G51: 14 | H51: 5000 | I51: 25 | J51: 52500 | K51: 3000 | L51: 42000 | M51: Returning | N51: EasyPaisa | O51: Returned
A52: ORD-1264 | B52: 2024-03-12 | C52: Sara Khan | D52: Multan | E52: Electronics | F52: Mobile Phone | G52: 14 | H52: 25000 | I52: 5 | J52: 332500 | K52: 18000 | L52: 252000 | M52: New | N52: Debit Card | O52: Pending
A53: ORD-1269 | B53: 2024-10-11 | C53: Kamran Sheikh | D53: Faisalabad | E53: Electronics | F53: Mobile Phone | G53: 3 | H53: 25000 | I53: 10 | J53: 67500 | K53: 18000 | L53: 54000 | M53: New | N53: EasyPaisa | O53: Delivered
A54: ORD-1282 | B54: 2024-08-08 | C54: Sara Khan | D54: Karachi | E54: Electronics | F54: Tablet | G54: 8 | H54: 35000 | I54: 20 | J54: 224000 | K54: 26000 | L54: 208000 | M54: New | N54: JazzCash | O54: Delivered
A55: ORD-1305 | B55: 2024-02-17 | C55: Zara Butt | D55: Multan | E55: Electronics | F55: Smartwatch | H55: 15000 | J55: 185250 | K55: 10000 | L55: 130000
A56: ORD-1316 | B56: 2024-11-03 | C56: Nadia Iqbal | D56: Karachi | E56: Electronics | F56: Tablet | H56: 35000 | J56: 196000 | K56: 26000 | L56: 182000
A57: ORD-1319 | B57: 2024-03-29 | C57: Zara Butt | D57: Lahore | E57: Electronics | F57: Smartwatch | G57: 3 | H57: 15000 | I57: 0 | J57: 45000 | K57: 10000 | L57: 30000 | M57: Returning | N57: Credit Card | O57: Delivered
A58: ORD-1328 | B58: 2024-07-15 | C58: Bilal Hussain | D58: Islamabad | E58: Electronics | F58: Smartwatch | G58: 14 | H58: 15000 | J58: 199500 | K58: 10000 | L58: 140000 | M58: Returning | N58: Credit Card | O58: Delivered
A59: ORD-1330 | B59: 2024-09-21 | C59: Ahmed Ali | D59: Karachi | E59: Electronics | F59: Headphones | G59: 10 | H59: 5000 | I59: 10 | J59: 45000 | K59: 3000 | L59: 30000 | M59: Returning | O59: Delivered
A60: ORD-1333 | B60: 2024-12-21 | C60: Ahmed Ali | D60: Multan | E60: Electronics | F60: Headphones | G60: 10 | H60: 5000 | I60: 0 | J60: 50000 | K60: 3000 | L60: 30000 | M60: New | N60: EasyPaisa | O60: Returned
A61: ORD-1339 | B61: 2024-08-25 | C61: Usman Raza | D61: Lahore | E61: Electronics | F61: Laptop | H61: 85000 | J61: 637500 | K61: 65000 | L61: 650000
A62: ORD-1342 | B62: 2024-03-12 | C62: Sara Khan | D62: Karachi | E62: Electronics | F62: Laptop | H62: 85000 | J62: 403750 | K62: 65000 | L62: 325000
A63: ORD-1343 | B63: 2024-11-26 | C63: Sara Khan | D63: Karachi | E63: Electronics | F63: Mobile Phone | G63: 3 | H63: 25000 | I63: 5 | J63: 71250 | K63: 18000 | L63: 54000 | M63: Returning | N63: Credit Card | O63: Delivered
A64: ORD-1349 | B64: 2024-06-12 | C64: Nadia Iqbal | D64: Peshawar | E64: Electronics | F64: Tablet | H64: 35000 | I64: 15 | J64: 59500 | K64: 26000 | L64: 52000 | M64: Returning | N64: EasyPaisa
A65: ORD-1355 | B65: 2024-03-13 | C65: Sara Khan | D65: Multan | E65: Electronics | F65: Tablet | G65: 13 | H65: 35000 | I65: 20 | J65: 364000 | K65: 26000 | L65: 338000 | M65: New | N65: Debit Card | O65: Delivered
A66: ORD-1359 | B66: 2024-09-11 | C66: Bilal Hussain | D66: Multan | E66: Electronics | F66: Laptop | G66: 12 | H66: 85000 | I66: 10 | J66: 918000 | K66: 65000 | L66: 780000 | M66: New | N66: Bank Transfer | O66: Shipped
A67: ORD-1360 | B67: 2024-02-15 | C67: Ayesha Siddiqui | D67: Rawalpindi | E67: Electronics | F67: Tablet | G67: 7 | H67: 35000 | I67: 5 | J67: 232750 | K67: 26000 | L67: 182000 | M67: New | N67: Debit Card | O67: Delivered
A68: ORD-1362 | B68: 2024-06-28 | C68: Kamran Sheikh | D68: Faisalabad | E68: Electronics | F68: Headphones | G68: 19 | H68: 5000 | I68: 25 | J68: 71250 | K68: 3000 | L68: 57000 | M68: New | N68: Credit Card | O68: Delivered
A69: ORD-1368 | B69: 2024-09-02 | C69: Fatima Malik | D69: Lahore | E69: Electronics | F69: Laptop | G69: 6 | H69: 85000 | I69: 25 | J69: 382500 | K69: 65000 | L69: 390000 | M69: Returning | N69: Cash | O69: Delivered
A70: ORD-1377 | B70: 2024-03-16 | C70: Nadia Iqbal | D70: Lahore | E70: Electronics | F70: Smartwatch | G70: 4 | H70: 15000 | I70: 10 | J70: 54000 | K70: 10000 | L70: 40000 | M70: Returning | N70: JazzCash | O70: Delivered
A71: ORD-1378 | B71: 2024-12-01 | C71: Zara Butt | D71: Rawalpindi | E71: Electronics | F71: Laptop | G71: 9 | H71: 85000 | I71: 15 | J71: 650250 | K71: 65000 | L71: 585000 | M71: New | N71: EasyPaisa | O71: Pending
A72: ORD-1382 | B72: 2024-07-27 | C72: Zara Butt | D72: Multan | E72: Electronics | F72: laptop | H72: 15000 | J72: 90000 | K72: 10000 | L72: 60000
A73: ORD-1386 | B73: 2024-05-12 | C73: Sara Khan | D73: Quetta | E73: Electronics | F73: Headphones | G73: 2 | H73: 5000 | I73: 5 | J73: 9500 | K73: 3000 | L73: 6000 | M73: New | N73: Credit Card | O73: Pending
A74: ORD-1401 | B74: 2024-08-07 | C74: Zara Butt | D74: Faisalabad | E74: Electronics | F74: Mobile Phone | G74: 18 | H74: 25000 | I74: 5 | J74: 427500 | K74: 18000 | L74: 324000 | M74: Returning | N74: Cash
A75: ORD-1402 | B75: 2024-09-28 | C75: Fatima Malik | D75: Karachi | E75: Electronics | F75: Laptop | H75: 85000 | J75: 510000 | K75: 65000 | L75: 520000
A76: ORD-1407 | B76: 2024-12-04 | C76: Sara Khan | D76: Karachi | E76: Electronics | F76: Mobile Phone | G76: 14 | H76: 25000 | I76: 15 | J76: 297500 | K76: 18000 | L76: 252000 | M76: Returning | N76: Cash | O76: Delivered
A77: ORD-1408 | B77: 2024-08-30 | C77: Bilal Hussain | D77: Peshawar | E77: Electronics | F77: Tablet | G77: 14 | H77: 35000 | I77: 25 | J77: 367500 | K77: 26000 | L77: 364000 | M77: New | N77: Bank Transfer | O77: Delivered
A78: ORD-1417 | B78: 2024-03-26 | C78: Sara Khan | D78: Karachi | E78: Electronics | F78: Laptop | G78: 4 | H78: 85000 | I78: 15 | J78: 289000 | K78: 65000 | L78: 260000 | M78: Returning | N78: EasyPaisa | O78: Pending
A79: ORD-1419 | B79: 2024-02-27 | C79: Hassan Mirza | D79: Rawalpindi | E79: Electronics | F79: Mobile Phone | H79: 25000 | J79: 168750 | K79: 18000 | L79: 162000
A80: ORD-1425 | B80: 2024-02-22 | C80: Hassan Mirza | D80: Faisalabad | E80: Electronics | F80: Smartwatch | G80: 18 | H80: 15000 | I80: 0 | J80: 270000 | K80: 10000 | L80: 180000 | M80: New | N80: EasyPaisa | O80: Cancelled
A81: ORD-1428 | B81: 2024-11-20 | C81: Usman Raza | D81: Multan | E81: Electronics | F81: Mobile Phone | G81: 6 | H81: 25000 | I81: 15 | J81: 127500 | K81: 18000 | L81: 108000 | M81: New | N81: Bank Transfer | O81: Pending
A82: ORD-1431 | B82: 2024-09-15 | C82: Bilal Hussain | D82: Rawalpindi | E82: Electronics | F82: Smartwatch | G82: 2 | H82: 15000 | I82: 20 | J82: 24000 | K82: 10000 | L82: 20000 | M82: Returning | N82: EasyPaisa | O82: Delivered
A83: ORD-1446 | B83: 2024-10-05 | C83: Kamran Sheikh | D83: Faisalabad | E83: Electronics | F83: Tablet | G83: 8 | H83: 35000 | I83: 5 | J83: 266000 | K83: 26000 | L83: 208000 | M83: Returning | N83: Debit Card | O83: Delivered
A84: ORD-1448 | B84: 2024-11-24 | C84: Nadia Iqbal | D84: Peshawar | E84: Electronics | F84: laptop | G84: 13 | H84: 35000 | I84: 0 | J84: 455000 | K84: 26000 | L84: 338000 | M84: Returning | N84: Debit Card | O84: Delivered
A85: ORD-1450 | B85: 2024-04-08 | C85: Ayesha Siddiqui | D85: Lahore | E85: Electronics | F85: Laptop | G85: 18 | H85: 85000 | I85: 20 | J85: 1224000 | K85: 65000 | L85: 1170000 | M85: New | N85: Bank Transfer
A86: ORD-1451 | B86: 2024-12-09 | C86: Fatima Malik | D86: Faislabad | E86: Electronics | F86: Laptop | G86: 18 | H86: 85000 | I86: 25 | J86: 1147500 | K86: 65000 | L86: 1170000 | M86: Returning | N86: Bank Transfer | O86: Shipped
A87: ORD-1456 | B87: 2024-08-12 | C87: Hassan Mirza | D87: Faisalabad | E87: Electronics | F87: Headphones | G87: 6 | H87: 5000 | I87: 20 | J87: 24000 | K87: 3000 | L87: 18000 | M87: New | N87: Credit Card | O87: Pending
A88: ORD-1479 | B88: 2024-11-22 | C88: Ahmed Ali | D88: Queta | E88: Electronics | F88: Laptop | G88: 15 | H88: 85000 | I88: 20 | J88: 1020000 | K88: 65000 | L88: 975000 | M88: Returning | N88: JazzCash | O88: Delivered
A89: ORD-1494 | B89: 2024-09-22 | C89: Usman Raza | D89: Karachi | E89: Electronics | F89: Smartwatch | G89: 17 | H89: 15000 | I89: 20 | J89: 204000 | K89: 10000 | L89: 170000 | M89: New | N89: EasyPaisa | O89: Delivered
A90: ORD-1495 | B90: 2024-01-19 | C90: Ayesha Siddiqui | D90: Peshawar | E90: Electronics | F90: Laptop | G90: 3 | H90: 85000 | I90: 10 | J90: 229500 | K90: 65000 | L90: 195000 | N90: Debit Card | O90: Pending
A91: ORD-1238 | B91: 2024-01-09 | C91: Fatima Malik | D91: Peshawar | E91: Electronics | F91: Mobile Phone | G91: 20 | H91: 25000 | I91: 0 | J91: 500000 | K91: 18000 | L91: 360000 | M91: Returning | N91: EasyPaisa | O91: Pending
A92: ORD-1177 | B92: 2024-07-07 | C92: Kamran Sheikh | D92: Quetta | E92: Electronics | F92: Headphones | G92: 3 | H92: 5000 | I92: 15 | J92: 12750 | K92: 3000 | L92: 9000 | M92: New | N92: EasyPaisa | O92: Delivered
A93: ORD-1137 | B93: 2024-03-14 | C93: Nadia Iqbal | D93: Faisalabad | E93: Electronics | F93: Laptop | G93: 1 | H93: 85000 | I93: 0 | J93: 85000 | K93: 65000 | L93: 65000 | M93: New | N93: JazzCash | O93: Delivered
A94: ORD-1132 | B94: 2024-02-13 | C94: Sara Khan | D94: Faisalabad | E94: Electronics | F94: Tablet | G94: 5 | H94: 35000 | I94: 20 | J94: 140000 | K94: 26000 | L94: 130000 | M94: New | O94: Cancelled
A95: ORD-1407 | B95: 2024-12-04 | C95: Sara Khan | D95: Karachi | E95: Electronics | F95: Mobile Phone | G95: 14 | H95: 25000 | I95: 15 | J95: 297500 | K95: 18000 | L95: 252000 | M95: Returning | N95: Cash | O95: Delivered

Sheet clean_sales data
A1: Order ID | B1: Date | C1: Salesperson | D1: Region | E1: Category | F1: Product Name | G1: Units Sold | H1: Unit Price (PKR) | I1: Discount % | J1: Total Revenue (PKR) | K1: Cost Price (Unit) | L1: Total Cost (PKR) | M1: Profit (PKR) | N1: Margin | O1: Customer Type | P1: Payment Method | Q1: Delivery Status | R1: Month
A2: ORD-1002 | B2: 2024-10-06 | C2: Sara Khan | D2: Faisalabad | E2: Electronics | F2: Mobile Phone | G2: 3 | H2: 25000 | I2: 5 | J2: 71250 | K2: 18000 | L2: 54000 | M2: 17250 | N2: =M2/J2 -> 0.24210526 | O2: New | P2: EasyPaisa | Q2: Pending | R2: =TEXT(B2,"MMM") -> Oct
A3: ORD-1005 | B3: 2024-06-25 | C3: Nadia Iqbal | D3: Quetta | E3: Electronics | F3: Headphones | G3: 18 | H3: 5000 | I3: 0 | J3: 90000 | K3: 3000 | L3: 54000 | M3: 36000 | N3: =M3/J3 -> 0.4 | O3: Returning | P3: Cash | Q3: Delivered | R3: =TEXT(B3,"MMM") -> Jun
A4: ORD-1012 | B4: 2024-03-11 | C4: Kamran Sheikh | D4: Rawalpindi | E4: Electronics | F4: Mobile Phone | G4: 4 | H4: 25000 | I4: 5 | J4: 95000 | K4: 18000 | L4: 72000 | M4: 23000 | N4: =M4/J4 -> 0.24210526 | O4: New | P4: Bank Transfer | Q4: Delivered | R4: =TEXT(B4,"MMM") -> Mar
A5: ORD-1021 | B5: 2024-11-19 | C5: Ahmed Ali | D5: Peshawar | E5: Electronics | F5: Mobile Phone | G5: 11 | H5: 25000 | I5: 0 | J5: 275000 | K5: 18000 | L5: 198000 | M5: 77000 | N5: =M5/J5 -> 0.28 | O5: New | P5: Debit Card | Q5: Pending | R5: =TEXT(B5,"MMM") -> Nov
A6: ORD-1026 | B6: 2024-11-29 | C6: Kamran Sheikh | D6: Karachi | E6: Electronics | F6: Laptop | G6: 6 | H6: 85000 | I6: 15 | J6: 433500 | K6: 65000 | L6: 390000 | M6: 43500 | N6: =M6/J6 -> 0.10034602 | O6: Returning | P6: JazzCash | Q6: Delivered | R6: =TEXT(B6,"MMM") -> Nov
A7: ORD-1030 | B7: 2024-02-04 | C7: Fatima Malik | D7: Faisalabad | E7: Electronics | F7: Smartwatch | G7: 8 | H7: 15000 | I7: 20 | J7: 96000 | K7: 10000 | L7: 80000 | M7: 16000 | N7: =M7/J7 -> 0.16666667 | O7: New | P7: EasyPaisa | Q7: Delivered | R7: =TEXT(B7,"MMM") -> Feb
A8: ORD-1041 | B8: 2024-05-07 | C8: Usman Raza | D8: Islamabad | E8: Electronics | F8: Headphones | G8: 2 | H8: 5000 | I8: 15 | J8: 8500 | K8: 3000 | L8: 6000 | M8: 2500 | N8: =M8/J8 -> 0.29411765 | O8: New | P8: Credit Card | Q8: Shipped | R8: =TEXT(B8,"MMM") -> May
A9: ORD-1044 | B9: 2024-05-13 | C9: Bilal Hussain | D9: Quetta | E9: Electronics | F9: Mobile Phone | G9: 20 | H9: 25000 | I9: 15 | J9: 425000 | K9: 18000 | L9: 360000 | M9: 65000 | N9: =M9/J9 -> 0.15294118 | O9: Returning | P9: Bank Transfer | Q9: Shipped | R9: =TEXT(B9,"MMM") -> May
A10: ORD-1051 | B10: 2024-04-11 | C10: Bilal Hussain | D10: Karachi | E10: Electronics | F10: Laptop | G10: 16 | H10: 85000 | I10: 20 | J10: 1088000 | K10: 65000 | L10: 1040000 | M10: 48000 | N10: =M10/J10 -> 0.044117647 | O10: New | P10: JazzCash | Q10: Delivered | R10: =TEXT(B10,"MMM") -> Apr
A11: ORD-1057 | B11: 2024-12-21 | C11: Bilal Hussain | D11: Peshawar | E11: Electronics | F11: Headphones | G11: 14 | H11: 5000 | I11: 10 | J11: 63000 | K11: 3000 | L11: 42000 | M11: 21000 | N11: =M11/J11 -> 0.33333333 | O11: Returning | P11: JazzCash | Q11: Delivered | R11: =TEXT(B11,"MMM") -> Dec
A12: ORD-1066 | B12: 2024-07-11 | C12: Hassan Mirza | D12: Peshawar | E12: Electronics | F12: Smartwatch | G12: 8 | H12: 15000 | I12: 0 | J12: 120000 | K12: 10000 | L12: 80000 | M12: 40000 | N12: =M12/J12 -> 0.33333333 | O12: Returning | P12: Bank Transfer | Q12: Pending | R12: =TEXT(B12,"MMM") -> Jul
A13: ORD-1088 | B13: 2024-08-09 | C13: Ayesha Siddiqui | D13: Quetta | E13: Electronics | F13: Mobile Phone | G13: 8 | H13: 25000 | I13: 25 | J13: 150000 | K13: 18000 | L13: 144000 | M13: 6000 | N13: =M13/J13 -> 0.04 | O13: New | P13: Bank Transfer | Q13: Shipped | R13: =TEXT(B13,"MMM") -> Aug
... A90: ORD-1495 | B90: 2024-01-19 | C90: Ayesha Siddiqui | D90: Peshawar | E90: Electronics | F90: Laptop | G90: 3 | H90: 85000 | I90: 10 | J90: 229500 | K90: 65000 | L90: 195000 | M90: 34500 | N90: =M90/J90 -> 0.1503268 | O90: Returning | P90: Debit Card | Q90: Pending | R90: =TEXT(B90,"MMM") -> Jan

Sheet pivot and charts
J22: Region | K22: Sum of Total Revenue (PKR)
E23: =GETPIVOTDATA("Total Revenue (PKR)",$A$31,"Month","Dec") -> 3896000 | G23: =GETPIVOTDATA("Total Revenue (PKR)",$A$31,"Month","Jan") -> 1320000 | J23: Lahore | K23: 5986250
J24: Multan | K24: 4882500
E25: CAGR | F25: =(E23/G23)^(1/12)-1 -> 0.094385721 | H25: =(E23/G23)^(1/12)-1 -> 0.094385721 | J25: Karachi | K25: 4551000
J26: Islamabad | K26: 4516000
J27: Rawalpindi | K27: 4098500
E28: =GETPIVOTDATA("Total Revenue (PKR)",$A$31,"Month","Jan") -> 1320000 | J28: Faisalabad | K28: 3858500
J29: Quetta | K29: 2803250
J30: Peshawar | K30: 2626000
A31: Month | B31: Sum of Total Revenue (PKR) | J31: Grand Total | K31: 33322000
A32: Jan | B32: 1320000 | U32: =GETPIVOTDATA("Total Revenue (PKR)",'pivot and charts'!$A$87)+'pivot and charts'!A86 -> 33322000
A33: Feb | B33: 1092750
A34: Mar | B34: 4213000
A35: Apr | B35: 3602500
A36: May | B36: 4013500
A37: Jun | B37: 1304500
A38: Jul | B38: 2040000
A39: Aug | B39: 2193500
A40: Sep | B40: 4219500
A41: Oct | B41: 2615750
A42: Nov | B42: 2811000
A43: Dec | B43: 3896000
A44: Grand Total | B44: 33322000
A52: Payment Method | B52: Count of Payment Method
A53: EasyPaisa | B53: 0.20224719
A54: Bank Transfer | B54: 0.19101124
A55: JazzCash | B55: 0.17977528
A56: Credit Card | B56: 0.15730337
A57: Cash | B57: 0.15730337
A58: Debit Card | B58: 0.11235955 | K58: Salesperson | L58: Sum of Total Revenue (PKR)
A59: Grand Total | B59: 1 | K59: Ahmed Ali | L59: 2053250
K60: Ayesha Siddiqui | L60: 4581500
K61: Bilal Hussain | L61: 6373000
K62: Fatima Malik | L62: 4111250
K63: Hassan Mirza | L63: 1099000
K64: Kamran Sheikh | L64: 1004750
K65: Nadia Iqbal | L65: 4337750
K66: Sara Khan | L66: 4315500
K67: Usman Raza | L67: 2618000
K68: Zara Butt | L68: 2828000
A69: Product Name | B69: Sum of Total Revenue (PKR) | K69: Grand Total | L69: 33322000
A70: Laptop | B70: 22095750
A71: Tablet | B71: 4686500
A72: Mobile Phone | B72: 4251250
A73: Smartwatch | B73: 1695750
A74: Headphones | B74: 592750
A75: Grand Total | B75: 33322000
A87: Total Revenue (PKR) | C87: Total Profit (PKR) | F87: Total Orders
A88: 33322000 | C88: 3604000 | F88: 89
H90: Customer Type | I90: Sum of Total Revenue (PKR)
H91: New | I91: 17503000
A92: Total Units Sold | C92: Average Profit Margin | H92: Returning | I92: 15819000
A93: 925 | C93: 0.17679671 | H93: Grand Total | I93: 33322000

Sheet Dashboard
F6: totagsahsbasbas
D43: =GETPIVOTDATA("Units Sold",'pivot and charts'!$A$92) -> 925 | E43: =GETPIVOTDATA("Margin",'pivot and charts'!$C$92) -> 0.17679671 | F43: =GETPIVOTDATA("Total Revenue (PKR)",'pivot and charts'!$A$87) -> 33322000 | H43: =GETPIVOTDATA("Profit (PKR)",'pivot and charts'!$C$87) -> 3604000
